{
  "parent": "block/cube",
  "textures": {
    "down": "survival_of_the_minecraftist:blocks/hell_coal_ore_nether",
    "up": "survival_of_the_minecraftist:blocks/hell_coal_ore_nether",
    "north": "survival_of_the_minecraftist:blocks/coal_ore_nether_side",
    "east": "survival_of_the_minecraftist:blocks/coal_ore_nether_side",
    "south": "survival_of_the_minecraftist:blocks/coal_ore_nether_side",
    "west": "survival_of_the_minecraftist:blocks/coal_ore_nether_side",
    "particle": "survival_of_the_minecraftist:blocks/hell_coal_ore_nether"
  }
}